merkle_example/__init__.py
merkle_example/__main__.py
merkle_example/example1.py
merkle_example/example2.py
merkle_example2/__init__.py
merkle_example2/__main__.py
merkle_example2/example2.py
minimal_example_project-1.0.3.dist-info/METADATA
minimal_example_project-1.0.3.dist-info/WHEEL
minimal_example_project-1.0.3.dist-info/top_level.txt
minimal_example_project-1.0.3.dist-info/RECORD
