Metadata-Version: 2.1
Name: minimal-example-project
Version: 1.0.3
Summary: a minimal Python project example with unit testing, command line interface, PyPi publishing capabilities
Home-page: https://github.com/michel-lacle/minimal_example_project
Author: Michel Lacle
Author-email: michel+pypi@f1kart.com
License: UNKNOWN
Platform: UNKNOWN
Requires-Dist: attrs (==20.3.0)
Requires-Dist: botocore (==1.19.30)
Requires-Dist: click (==7.1.2)
Requires-Dist: iniconfig (==1.1.1)
Requires-Dist: jmespath (==0.10.0)
Requires-Dist: packaging (==20.7)
Requires-Dist: pluggy (==0.13.1)
Requires-Dist: py (==1.9.0)
Requires-Dist: pyparsing (==2.4.7)
Requires-Dist: pytest (==6.1.2)
Requires-Dist: python-dateutil (==2.8.1)
Requires-Dist: six (==1.15.0)
Requires-Dist: toml (==0.10.2)
Requires-Dist: urllib3 (==1.26.2)
